pyscoresaber/__init__.py
pyscoresaber/errors.py
pyscoresaber/http_client.py
pyscoresaber/scoresaber.py
pyscoresaber/scoresaber_api.py
pyscoresaber/scoresaber_provider.py
pyscoresaber/version.py
pyscoresaber/models/__init__.py
pyscoresaber/models/badge.py
pyscoresaber/models/difficulty.py
pyscoresaber/models/fields.py
pyscoresaber/models/leaderboard_info.py
pyscoresaber/models/leaderboard_info_collection.py
pyscoresaber/models/leaderboard_player.py
pyscoresaber/models/metadata.py
pyscoresaber/models/player.py
pyscoresaber/models/player_collection.py
pyscoresaber/models/player_score.py
pyscoresaber/models/player_scores_collection.py
pyscoresaber/models/score.py
pyscoresaber/models/score_collection.py
pyscoresaber/models/score_stats.py
pyscoresaber/models/enum/__init__.py
pyscoresaber/models/enum/base_enum.py
pyscoresaber/models/enum/beatmap_difficulty.py
pyscoresaber/models/enum/category.py
pyscoresaber/models/enum/game_mode.py
pyscoresaber/models/enum/score_sort.py
pyscoresaber/models/enum/sort.py
PyScoreSaber-1.0.10.dist-info/LICENSE
PyScoreSaber-1.0.10.dist-info/METADATA
PyScoreSaber-1.0.10.dist-info/WHEEL
PyScoreSaber-1.0.10.dist-info/top_level.txt
PyScoreSaber-1.0.10.dist-info/RECORD
