Metadata-Version: 2.1
Name: PyScoreSaber
Version: 1.0.10
Summary: Score Saber API wrapper
Home-page: https://github.com/Kiyomi-Parents/PyScoreSaber
Author: LuCkEr-
Author-email: lucker@lucker.xyz
Project-URL: Bug Tracker, https://github.com/Kiyomi-Parents/PyScoreSaber/issues
Classifier: Programming Language :: Python :: 3.8
Classifier: Programming Language :: Python :: 3.9
Classifier: Programming Language :: Python :: 3.10
Classifier: License :: OSI Approved :: MIT License
Classifier: Operating System :: OS Independent
Classifier: Intended Audience :: Developers
Classifier: Natural Language :: English
Classifier: Topic :: Internet
Classifier: Topic :: Software Development :: Libraries
Classifier: Topic :: Software Development :: Libraries :: Python Modules
Classifier: Topic :: Utilities
Classifier: Typing :: Typed
Requires-Python: >=3.8
License-File: LICENSE
Requires-Dist: python-dateutil (~=2.8.2)
Requires-Dist: OutCache (~=1.0.1)
Requires-Dist: marshmallow (~=3.19.0)
Requires-Dist: dataclasses-json (~=0.5.7)
Requires-Dist: aiohttp (~=3.8.3)
Requires-Dist: Faker (~=15.3.3)
Provides-Extra: test
Requires-Dist: coverage ; extra == 'test'
Requires-Dist: pytest ; extra == 'test'
Requires-Dist: pytest-asyncio ; extra == 'test'
Requires-Dist: pytest-cov ; extra == 'test'
